spacebar_counter/__init__.py
spacebar_counter/cli.py
spacebar_counter-0.1.2.dist-info/licenses/LICENSE
spacebar_counter-0.1.2.dist-info/METADATA
spacebar_counter-0.1.2.dist-info/WHEEL
spacebar_counter-0.1.2.dist-info/entry_points.txt
spacebar_counter-0.1.2.dist-info/top_level.txt
spacebar_counter-0.1.2.dist-info/RECORD
