Metadata-Version: 2.4
Name: spacebar-counter
Version: 0.1.2
Summary: A CLI tool to count spacebar presses.
Author: Your Name
Requires-Python: >=3.7
License-File: LICENSE
Requires-Dist: pynput
Requires-Dist: plotly
Requires-Dist: typer
Dynamic: author
Dynamic: description
Dynamic: description-content-type
Dynamic: license-file
Dynamic: requires-dist
Dynamic: requires-python
Dynamic: summary
